{"id":"06ed4272-d97a-58d5-944a-e1b6e64fd717","name":"4.9","type":"text","x":1774.166748046875,"y":-163,"width":93,"height":82,"rotation":0,"selrect":{"x":1774.166748046875,"y":-163,"width":93,"height":82,"x1":1774.166748046875,"y1":-163,"x2":1867.166748046875,"y2":-81},"points":[{"x":1774.166748046875,"y":-163},{"x":1867.166748046875,"y":-163},{"x":1867.166748046875,"y":-81},{"x":1774.166748046875,"y":-81}],"transform":{"a":1,"b":0,"c":0,"d":1,"e":0,"f":0},"transformInverse":{"a":1,"b":0,"c":0,"d":1,"e":0,"f":0},"parentId":"eaa8c0cf-87fb-5e7b-a851-7bda29493a51","frameId":"eaa8c0cf-87fb-5e7b-a851-7bda29493a51","flipX":null,"flipY":null,"layoutItemAbsolute":false,"growType":"auto-width","content":{"type":"root","verticalAlign":"top","children":[{"type":"paragraph-set","children":[{"lineHeight":"1.2","fontStyle":"normal","children":[{"lineHeight":"1.2","fontStyle":"normal","textTransform":"capitalize","textAlign":"left","fontId":"gfont-manrope","fontSize":"60","fontWeight":"800","fontVariantId":"800","fillStyleId":"S:ffd52a8ebb3ba5c820b92c9accc232e08bcec4ed,","textDecoration":"none","letterSpacing":"0","fills":[{"fillColor":"#ffffff","fillOpacity":1,"fillColorRefId":"7007bf74-b438-8031-8007-c9adb249e5cf","fillColorRefFile":"7007bf74-b438-8031-8007-c9adb1e0ad56"}],"fontFamily":"Manrope","text":"4.9"}],"textTransform":"capitalize","textAlign":"left","fontId":"gfont-manrope","fontSize":"60","fontWeight":"800","type":"paragraph","fontVariantId":"800","fillStyleId":"S:ffd52a8ebb3ba5c820b92c9accc232e08bcec4ed,","textDecoration":"none","letterSpacing":"0","fills":[{"fillColor":"#ffffff","fillOpacity":1,"fillColorRefId":"7007bf74-b438-8031-8007-c9adb249e5cf","fillColorRefFile":"7007bf74-b438-8031-8007-c9adb1e0ad56"}],"fontFamily":"Manrope"}]}]},"blendMode":"normal","touched":[],"layoutItemHSizing":"fix","proportionLock":false,"pageId":"7007bf74-b438-8031-8007-c9adb2662682","layoutItemVSizing":"fix","constraintsV":"top","constraintsH":"left","hidden":false,"opacity":1,"appliedTokens":{},"strokes":[],"blocked":false,"shadow":[],"layoutItemAlignSelf":"stretch"}