{"id":"a92f7280-f23d-5696-8d1d-ac01588a5130","name":"Enroll Now_2","type":"text","x":836,"y":-437,"width":133,"height":22,"rotation":0,"selrect":{"x":836,"y":-437,"width":133,"height":22,"x1":836,"y1":-437,"x2":969,"y2":-415},"points":[{"x":836,"y":-437},{"x":969,"y":-437},{"x":969,"y":-415},{"x":836,"y":-415}],"transform":{"a":1,"b":0,"c":0,"d":1,"e":0,"f":0},"transformInverse":{"a":1,"b":0,"c":0,"d":1,"e":0,"f":0},"parentId":"755c9c76-84d6-53df-b6c9-0edd8138956a","frameId":"755c9c76-84d6-53df-b6c9-0edd8138956a","flipX":null,"flipY":null,"layoutItemAbsolute":false,"growType":"auto-width","content":{"type":"root","verticalAlign":"top","children":[{"type":"paragraph-set","children":[{"lineHeight":"1.2","fontStyle":"normal","children":[{"lineHeight":"1.2","fontStyle":"normal","textTransform":"capitalize","textAlign":"center","fontId":"gfont-manrope","fontSize":"16","fontWeight":"700","fontVariantId":"700","textDecoration":"none","letterSpacing":"0","fills":[{"fillColor":"#ffffff","fillOpacity":1}],"fontFamily":"Manrope","text":"Explore Products"}],"textTransform":"capitalize","textAlign":"center","fontId":"gfont-manrope","fontSize":"16","fontWeight":"700","type":"paragraph","fontVariantId":"700","textDecoration":"none","letterSpacing":"0","fills":[{"fillColor":"#ffffff","fillOpacity":1}],"fontFamily":"Manrope"}]}]},"blendMode":"normal","touched":[],"layoutItemHSizing":"fix","proportionLock":false,"pageId":"7007bf74-b438-8031-8007-c9adb2662682","layoutItemVSizing":"fix","constraintsV":"top","constraintsH":"left","hidden":false,"opacity":1,"appliedTokens":{},"strokes":[],"blocked":false,"shadow":[],"layoutItemAlignSelf":"stretch"}